{
    "610961_mid": "Non c'è bisogno di presentazioni, vero?\nAllora... iniziamo!",
    "610965_mid": "Uhhh... Spero che non siate rimasti bruciati\ne ridotti in cenere a forza di studiare...",
    "610961_end": "Me raccomanno, teneteve pronti!",
    "610965_end": "Sarete in grado tu e la tua squadra di superare\nquesto esame?",
    "611046_mid": "Anche se vi sentite pronti per l'esame, vi consiglio\ndi non abbassare la guardia!",
    "611046_end": "Abbiamo studiato instancabilmente, e ora siamo\npronti a mostrarvi i frutti dei nostri sforzi!",
    "611100_mid": "Non c'è bisogno di presentazioni, vero?\nAllora... iniziamo!",
    "611100_end": "Me raccomanno, teneteve pronti!",
    "611215_mid": "La vita è una partita che ognuno gioca con le carte\nche ha ricevuto. Hai nuove carte dopo i tuoi studi?",
    "611215_end": "Avete affrontato molte lotte e imparato tanto. Ora\nsfidatemi e mostratemi quanto siete diventati forti!"
}
