{
    "1": "[Name:EventName ] im Gange!",
    "2": "Strebe den Spitzenrang mit deinen Arena-Mitgliedern an!",
    "4": "Erster Kampf von [Name:PlayerNickname ]: [Name:TrainerName ]!",
    "5": "[Name:PlayerNickname ] kämpft gegen [Name:TrainerName ]!",
    "6": "[Name:PlayerNickname ] hat [Name:TrainerName ] besiegt!",
    "7": "[Name:PlayerNickname ] siegte über [Name:TrainerName ]!",
    "8": "[Name:PlayerNickname ] stellt sich [Name:TrainerName ] als [DE:Gen Ref=\"255\" M=\"Erster\" F=\"Erste\" ]!",
    "9": "[Name:PlayerNickname ] nimmt es mit [Name:TrainerName ] auf!",
    "10": "[Name:PlayerNickname ] tritt gegen [Name:TrainerName ] an!",
    "11": "[Name:PlayerNickname ] tritt dem Arenakampf bei! Hilfe kann nicht schaden!",
    "12": "[Name:PlayerNickname ] tritt dem Arenakampf bei!",
    "13": "[Name:PlayerNickname ] besiegt [Name:TrainerName ] im Alleingang!",
    "14": "[Name:PlayerNickname ] besiegt [Name:TrainerName ] ganz allein!",
    "15": "[Name:TrainerName ] ist fast besiegt!",
    "16": "[Name:TrainerName ] steht unter Druck!",
    "17": "[Name:TrainerName ] ist am Limit! Der Sieg ist zum Greifen nah!",
    "18": "Der Kampf gegen [Name:TrainerName ] ist fast vorbei!",
    "19": "[Name:PlayerNickname ] setzt [Name:TrainerName ] unter Druck!",
    "20": "[Name:PlayerNickname ] hat sich gegen [Name:TrainerName ] behauptet!",
    "21": "[Name:PlayerNickname ] hat [Name:TrainerName ] ordentlich zugesetzt!",
    "22": "[Name:TrainerName ] wurde nach [Digit:3digits ] [DE:Qty S=\"Versuch\" P=\"Versuchen\" ] besiegt!",
    "23": "Das Pokémon von [Name:TrainerName ] schläft tief und fest!",
    "24": "Der Passio-Arenakampf endet in [Digit:3digits ] [DE:Qty S=\"Tag\" P=\"Tagen\" ]! Geben wir alles!",
    "25": "Der Passio-Arenakampf endet in [Digit:3digits ] [DE:Qty S=\"Tag\" P=\"Tagen\" ]! Nicht aufgeben!",
    "26": "[Name:PlayerNickname ] versucht sich heute erneut am Arenakampf!",
    "27": "[Name:PlayerNickname ] will sich erneut im Arenakampf messen!",
    "28": "[Name:PlayerNickname ] ist im Arenakampf erneut an vorderster Front!"
}
