{
    "150000001": "Noble Style",
    "150000002": "Natural Style",
    "152020101": "Earth Badge",
    "152020201": "Rainbow Wing",
    "152020202": "Ho-Oh Plaque",
    "152020301": "Wailmer Pail",
    "152020401": "Old Charm",
    "152020402": "Dawn’s Hat",
    "152020501": "Promo Card",
    "152020502": "N’s Cube",
    "152020503": "Elesa’s Headphones",
    "152020601": "Phonograph",
    "152020602": "Serena’s Hat",
    "152020701": "Poké Doll",
    "152020801": "Team Yell Towel",
    "152020802": "Rotom Phone",
    "152020803": "Gloria’s Bag",
    "152010001": "Objet: Pasio Tower",
    "152010002": "Objet: Wooden Star",
    "152010003": "Objet: Ice Tower",
    "152010004": "Objet: Red Stone",
    "152010005": "Objet: Moon Trophy",
    "152010006": "Objet: Wooden Metronome",
    "152010007": "Objet: Blue Tuning Fork",
    "152010008": "Objet: Wonder Stone",
    "152010009": "Objet: Star Trophy",
    "153000001": "[Name:TrainerName ] Plushie",
    "152020302": "Rare Stone",
    "152020702": "Acerola’s Armband",
    "152020403": "Diamond Clan Plaque",
    "150000003": "Hisui Style",
    "152020404": "Pearl Clan Plaque",
    "152020603": "Calem’s Hat",
    "152020102": "Leaf’s Hat",
    "150000004": "Team Rocket Style",
    "152020103": "Team Rocket Plaque"
}
