{
    "10000001": "공격",
    "10000002": "방어",
    "10000003": "특수공격",
    "10000004": "특수방어",
    "10000005": "스피드",
    "10000006": "명중률",
    "10000007": "회피율",
    "10000008": "급소율",
    "11000001": "공격",
    "11000002": "방어",
    "11000003": "특수공격",
    "11000004": "특수방어",
    "11000005": "스피드",
    "11000006": "명중률",
    "11000007": "회피율",
    "11000008": "급소율",
    "12000001": "공격",
    "12000002": "방어",
    "12000003": "특수공격",
    "12000004": "특수방어",
    "12000005": "스피드",
    "12000006": "명중률",
    "12000007": "회피율",
    "12000008": "급소율",
    "13000001": "공격",
    "13000003": "특수공격",
    "13000007": "회피율",
    "20020001": "관동 태그",
    "20020002": "성도 태그",
    "20020003": "호연 태그",
    "20020004": "신오 태그",
    "20020005": "하나 태그",
    "20020006": "칼로스 태그",
    "20020007": "알로라 태그",
    "20020008": "가라르 태그",
    "20020009": "팔데아 태그",
    "30010001": "물리",
    "30010002": "특수",
    "40000209": "교체금지",
    "40000214": "회피불가",
    "40000216": "버티기",
    "40000218": "지속회복",
    "40000222": "상태이상방해부여무효",
    "40000223": "차회발군위력상승",
    "40000224": "차회게이지소비0",
    "40000225": "차회데미지방어",
    "40000228": "차회물리기술위력부스트",
    "40000229": "차회특수기술위력부스트",
    "40000231": "불꽃타입 저항",
    "40000232": "물타입 저항",
    "40000233": "전기타입 저항",
    "40000234": "풀타입 저항",
    "40000235": "얼음타입 저항",
    "40000236": "격투타입 저항",
    "40000237": "독타입 저항",
    "40000238": "땅타입 저항",
    "40000240": "에스퍼타입 저항",
    "40000243": "고스트타입 저항",
    "40000244": "드래곤타입 저항",
    "40000245": "악타입 저항",
    "40000246": "강철타입 저항",
    "40000247": "페어리타입 저항",
    "40000301": "물리데미지경감",
    "40000302": "특수데미지경감",
    "40000307": "급소방어",
    "40000308": "상태이상방어",
    "40000317": "기술게이지가속",
    "40000322": "일렉트릭필드",
    "40000323": "그래스필드",
    "40000324": "사이코필드",
    "40000325": "순백존",
    "40000328": "고드름존",
    "40000329": "주먹존",
    "40000330": "맹독존",
    "40000331": "대지존",
    "40000332": "푸른하늘존",
    "40000333": "비단벌레존",
    "40000334": "암석존",
    "40000335": "원령존",
    "40000336": "용의존",
    "40000337": "공포존",
    "40000338": "강철존",
    "40000339": "정령존",
    "40000345": "불꽃타입 데미지 필드",
    "40000356": "바위타입 데미지 필드",
    "40000359": "악타입 데미지 필드",
    "40000360": "강철타입 데미지 필드",
    "40000362": "능력상승불가",
    "40000364": "관동서클(특수)",
    "40000366": "성도서클(물리)",
    "40000370": "호연서클(특수)",
    "40000375": "하나서클(물리)",
    "50000001": "노말",
    "50000002": "불꽃",
    "50000003": "물",
    "50000004": "전기",
    "50000005": "풀",
    "50000006": "얼음",
    "50000007": "격투",
    "50000008": "독",
    "50000009": "땅",
    "50000010": "비행",
    "50000011": "에스퍼",
    "50000012": "벌레",
    "50000013": "바위",
    "50000014": "고스트",
    "50000015": "드래곤",
    "50000016": "악",
    "50000017": "강철",
    "50000018": "페어리"
}
